{
  "id": "kanban-tactile",
  "name": "Kanban Tactile",
  "html": "<div class=\"widget-card\">\n  <h4 class=\"widget-title\">📱 Tactile Kanban</h4>\n  <div class=\"kanban-board\">\n    <div class=\"column\">\n      <div class=\"column-header\">TO DO</div>\n      <div class=\"input-area\">\n        <input type=\"text\" id=\"in-0\" placeholder=\"New task...\">\n        <button class=\"btn-add-inline\" id=\"btn-add-0\">+</button>\n      </div>\n      <div class=\"task-list\" id=\"list-0\"></div>\n    </div>\n\n    <div class=\"column\">\n      <div class=\"column-header\">DOING</div>\n      <div class=\"input-area\">\n        <input type=\"text\" id=\"in-1\" placeholder=\"New task...\">\n        <button class=\"btn-add-inline\" id=\"btn-add-1\">+</button>\n      </div>\n      <div class=\"task-list\" id=\"list-1\"></div>\n    </div>\n\n    <div class=\"column\">\n      <div class=\"column-header\">DONE</div>\n      <div class=\"input-area\">\n        <input type=\"text\" id=\"in-2\" placeholder=\"New task...\">\n        <button class=\"btn-add-inline\" id=\"btn-add-2\">+</button>\n      </div>\n      <div class=\"task-list\" id=\"list-2\"></div>\n    </div>\n  </div>\n</div>",
  "css": ":host { display: block; margin: 1.5rem 0; font-family: var(--font-interface); }\n.widget-card {\n    background: var(--background-secondary);\n    border: 1px solid var(--divider-color);\n    border-radius: 12px;\n    padding: 1.25rem;\n    box-shadow: 0 4px 12px rgba(0,0,0,0.08);\n}\n.widget-title { margin: 0 0 1.25rem 0; font-size: 0.9rem; font-weight: 600; color: var(--text-accent); text-align: center; text-transform: uppercase; letter-spacing: 0.05em; }\n\n.kanban-board {\n    display: flex;\n    gap: 12px;\n    overflow-x: auto;\n    padding-bottom: 8px;\n}\n\n.column {\n    flex: 1;\n    min-width: 220px;\n    background: var(--background-primary-alt);\n    border: 1px solid var(--divider-color);\n    border-radius: 10px;\n    display: flex;\n    flex-direction: column;\n    max-height: 500px;\n}\n\n.column-header { \n    padding: 12px;\n    font-size: 0.7rem; \n    font-weight: 800;\n    color: var(--text-accent);\n    text-align: center;\n    letter-spacing: 1px;\n    border-bottom: 1px solid var(--divider-color);\n}\n\n.input-area {\n    display: flex;\n    padding: 10px;\n    gap: 8px;\n    background: var(--background-secondary);\n}\n\n.input-area input {\n    flex: 1;\n    background: var(--background-primary);\n    border: 1px solid var(--divider-color);\n    color: var(--text-normal);\n    border-radius: 6px;\n    padding: 6px 10px;\n    font-size: 0.8rem;\n    outline: none;\n}\n.input-area input:focus { border-color: var(--interactive-accent); }\n\n.btn-add-inline {\n    background: var(--interactive-accent);\n    color: white;\n    border: none;\n    border-radius: 6px;\n    width: 32px;\n    height: 32px;\n    cursor: pointer;\n    font-weight: bold;\n}\n\n.task-list {\n    padding: 10px;\n    overflow-y: auto;\n    flex-grow: 1;\n}\n\n.task-card {\n    background: var(--background-primary);\n    border: 1px solid var(--divider-color);\n    border-radius: 8px;\n    padding: 12px;\n    margin-bottom: 10px;\n    box-shadow: 0 2px 6px rgba(0,0,0,0.05);\n}\n\n.task-content {\n    color: var(--text-normal);\n    font-size: 0.85rem;\n    margin-bottom: 10px;\n    display: block;\n    outline: none;\n    line-height: 1.4;\n}\n\n.task-footer {\n    display: flex;\n    justify-content: space-between;\n    border-top: 1px solid var(--divider-color);\n    padding-top: 8px;\n}\n\n.btn-move {\n    background: var(--background-secondary-alt);\n    border: 1px solid var(--divider-color);\n    color: var(--text-muted);\n    border-radius: 4px;\n    padding: 2px 8px;\n    font-size: 1rem;\n    cursor: pointer;\n}\n.btn-move:hover { color: var(--text-accent); border-color: var(--text-accent); }\n.btn-del { color: var(--text-error); font-size: 0.75rem; border: none; background: none; cursor: pointer; opacity: 0.7; }\n.btn-del:hover { opacity: 1; }",
  "js": "var data = [[], [], []];\n\nfunction addTask(colIdx) {\n    var input = api.root.getElementById('in-' + colIdx);\n    var val = input.value.trim();\n    if (val) {\n        data[colIdx].push(val);\n        input.value = '';\n        update();\n    }\n}\n\nfunction update() {\n    api.saveState(data);\n    render();\n}\n\nfunction render() {\n    for (var i = 0; i < 3; i++) {\n        var listEl = api.root.getElementById('list-' + i);\n        listEl.innerHTML = '';\n        \n        data[i].forEach(function(task, taskIdx) {\n            var card = document.createElement('div');\n            card.className = 'task-card';\n            \n            var leftBtn = i > 0 ? '<button class=\"btn-move m-left\">←</button>' : '';\n            var rightBtn = i < 2 ? '<button class=\"btn-move m-right\">→</button>' : '';\n            \n            card.innerHTML = '<div class=\"task-content\" contenteditable=\"true\">' + task + '</div>' +\n                '<div class=\"task-footer\">' +\n                    '<div>' + leftBtn + rightBtn + '</div>' +\n                    '<button class=\"btn-del\">Delete</button>' +\n                '</div>';\n\n            (function(colIdx, tIdx) {\n                var content = card.querySelector('.task-content');\n                content.onblur = function() {\n                    data[colIdx][tIdx] = content.innerText;\n                    api.saveState(data);\n                };\n\n                var btnLeft = card.querySelector('.m-left');\n                if(btnLeft) btnLeft.onclick = function() { move(colIdx, colIdx-1, tIdx); };\n\n                var btnRight = card.querySelector('.m-right');\n                if(btnRight) btnRight.onclick = function() { move(colIdx, colIdx+1, tIdx); };\n\n                card.querySelector('.btn-del').onclick = function() {\n                    data[colIdx].splice(tIdx, 1);\n                    update();\n                };\n            })(i, taskIdx);\n\n            listEl.appendChild(card);\n        });\n    }\n}\n\nfunction move(fromCol, toCol, idx) {\n    var item = data[fromCol].splice(idx, 1)[0];\n    data[toCol].push(item);\n    update();\n}\n\nasync function init() {\n    var saved = await api.getState();\n    if (saved) data = saved;\n    \n    for (var i = 0; i < 3; i++) {\n        (function(idx) {\n            api.root.getElementById('btn-add-' + idx).onclick = function() { addTask(idx); };\n            api.root.getElementById('in-' + idx).onkeydown = function(e) { if (e.key === 'Enter') addTask(idx); };\n        })(i);\n    }\n    \n    render();\n}\n\ninit();",
  "tags": [
    "productivity",
    "tasks",
    "organization"
  ]
}